updater_extension/__init__.py
updater_extension/updater_extension.py
updater_extension-0.1.0.dist-info/AUTHORS.rst
updater_extension-0.1.0.dist-info/LICENSE
updater_extension-0.1.0.dist-info/METADATA
updater_extension-0.1.0.dist-info/WHEEL
updater_extension-0.1.0.dist-info/top_level.txt
updater_extension-0.1.0.dist-info/RECORD
