Metadata-Version: 2.1
Name: updater-extension
Version: 0.1.0
Summary: Updater Extension is an Extension of the python-telegram-bot Updater class.
Home-page: https://github.com/Baribor/updater_extension
Author: Baribor Saturday
Author-email: saturdaybaribor@gmail.com
License: MIT license
Keywords: updater_extension
Classifier: Development Status :: 2 - Pre-Alpha
Classifier: Intended Audience :: Developers
Classifier: License :: OSI Approved :: MIT License
Classifier: Natural Language :: English
Classifier: Programming Language :: Python :: 3
Classifier: Programming Language :: Python :: 3.6
Classifier: Programming Language :: Python :: 3.7
Classifier: Programming Language :: Python :: 3.8
Classifier: Programming Language :: Python :: 3.9
Requires-Python: >=3.6
License-File: LICENSE
License-File: AUTHORS.rst
Requires-Dist: python-telegram-bot (>=13.11)
